{"hash":"63d5b43723263c8fdc2035c194f0c3efa4f81b4b","data":null,"context":{"id":"19128","sku":"11684304","name":"Browning Maxus Sporting Black Carbon 28\" Shotgun","slug":"browning-maxus-sporting-black-carbon-28-shotgun","status":"publish","excerpt":"<p>The Browning Maxus Sporting Black Carbon 28&#8243; Shotgun has been specially designed for sports shooting. Its carbon finish gives a particularly unique style.</p>\n","content":"<p>The Browning Maxus Sporting Black Carbon 28\" Shotgun has been specially designed for sports shooting. The ventilated rib, tapered from 6mm to 8mm, gives faster targeting. Its carbon finish gives a particularly unique style. </p>\n<p>Featuring Browning's Power Drive gas system, the Maxus Sporting Carbon Fibre has been designed to perform under harsh hunting and shooting conditions with a wide array of loads. The Maxus is supremely reliable and mostly maintenance-free.</p>\n","price":"1249","stockStatus":"instock","categories":[{"id":4098,"name":"Guns"},{"id":388,"name":"Semi Auto &amp; Pump"},{"id":375,"name":"Shotgun"}],"images":[{"src":"https://res.cloudinary.com/shooting-supplies/image/upload/v1575031915/Browning-Maxus-Carbon_nyjmeu_fhjn1i.jpg"}],"brands":[{"id":423,"name":"Browning"}]}}